tao_poetry_example/__init__.py
tao_poetry_example/cli.py
tao_poetry_example/increment.py
tao_poetry_example-0.1.0.dist-info/WHEEL
tao_poetry_example-0.1.0.dist-info/entry_points.txt
tao_poetry_example-0.1.0.dist-info/METADATA
tao_poetry_example-0.1.0.dist-info/RECORD
