Metadata-Version: 2.1
Name: tao-poetry-example
Version: 0.1.0
Summary: 
Author: Tao
Author-email: twang15@ncsu.edu
Requires-Python: >=3.9,<4.0
Classifier: Programming Language :: Python :: 3
Classifier: Programming Language :: Python :: 3.9
Classifier: Programming Language :: Python :: 3.10
Classifier: Programming Language :: Python :: 3.11
Requires-Dist: click (>=8.1.3,<9.0.0)
